c2cgeoform/__init__.py
c2cgeoform/ext/__init__.py
c2cgeoform/ext/colander_ext.py
c2cgeoform/ext/deform_ext.py
c2cgeoform/locale/Readme.md
c2cgeoform/locale/de/LC_MESSAGES/c2cgeoform.po
c2cgeoform/locale/fr/LC_MESSAGES/c2cgeoform.po
c2cgeoform/locale/it/LC_MESSAGES/c2cgeoform.po
c2cgeoform/models.py
c2cgeoform/py.typed
c2cgeoform/routes.py
c2cgeoform/scaffolds/c2cgeoform/cookiecutter.json
c2cgeoform/scaffolds/c2cgeoform/{{cookiecutter.project}}/+dot+gitignore
c2cgeoform/scaffolds/c2cgeoform/{{cookiecutter.project}}/MANIFEST.in
c2cgeoform/scaffolds/c2cgeoform/{{cookiecutter.project}}/Makefile
c2cgeoform/scaffolds/c2cgeoform/{{cookiecutter.project}}/README.txt
c2cgeoform/scaffolds/c2cgeoform/{{cookiecutter.project}}/acceptance_tests/__init__.py
c2cgeoform/scaffolds/c2cgeoform/{{cookiecutter.project}}/acceptance_tests/conftest.py
c2cgeoform/scaffolds/c2cgeoform/{{cookiecutter.project}}/acceptance_tests/excavation_test.py
c2cgeoform/scaffolds/c2cgeoform/{{cookiecutter.project}}/apache.conf
c2cgeoform/scaffolds/c2cgeoform/{{cookiecutter.project}}/development.ini
c2cgeoform/scaffolds/c2cgeoform/{{cookiecutter.project}}/lingua.cfg
c2cgeoform/scaffolds/c2cgeoform/{{cookiecutter.project}}/package.json
c2cgeoform/scaffolds/c2cgeoform/{{cookiecutter.project}}/production.ini
c2cgeoform/scaffolds/c2cgeoform/{{cookiecutter.project}}/requirements-dev.txt
c2cgeoform/scaffolds/c2cgeoform/{{cookiecutter.project}}/requirements.txt
c2cgeoform/scaffolds/c2cgeoform/{{cookiecutter.project}}/setup.cfg
c2cgeoform/scaffolds/c2cgeoform/{{cookiecutter.project}}/setup.py
c2cgeoform/scaffolds/c2cgeoform/{{cookiecutter.project}}/tests.ini
c2cgeoform/scaffolds/c2cgeoform/{{cookiecutter.project}}/{{cookiecutter.package}}/__init__.py
c2cgeoform/scaffolds/c2cgeoform/{{cookiecutter.project}}/{{cookiecutter.package}}/data/osm-lausanne-bus-stops.geojson
c2cgeoform/scaffolds/c2cgeoform/{{cookiecutter.project}}/{{cookiecutter.package}}/i18n.py
c2cgeoform-2.5.0.dist-info/METADATA
c2cgeoform-2.5.0.dist-info/WHEEL
c2cgeoform-2.5.0.dist-info/entry_points.txt
c2cgeoform-2.5.0.dist-info/RECORD
