Metadata-Version: 2.3
Name: c2cgeoform
Version: 2.5.0
Summary: c2cgeoform
Keywords: web,wsgi,bfg,pylons,pyramid
Author: Camptocamp
Author-email: info@camptocamp.com
Requires-Python: >=3.11
Classifier: Framework :: Pyramid
Classifier: Programming Language :: Python
Classifier: Programming Language :: Python :: 3
Classifier: Programming Language :: Python :: 3.11
Classifier: Programming Language :: Python :: 3.12
Classifier: Programming Language :: Python :: 3.13
Classifier: Topic :: Internet :: WWW/HTTP
Classifier: Topic :: Internet :: WWW/HTTP :: WSGI :: Application
Classifier: Typing :: Typed
Provides-Extra: psycopg2
Provides-Extra: psycopg2-binary
Requires-Dist: babel
Requires-Dist: colanderalchemy
Requires-Dist: deform
Requires-Dist: geoalchemy2
Requires-Dist: geojson
Requires-Dist: lingua
Requires-Dist: psycopg2 ; extra == "psycopg2"
Requires-Dist: psycopg2-binary ; extra == "psycopg2-binary"
Requires-Dist: pyproj
Requires-Dist: pyramid
Requires-Dist: pyramid-beaker
Requires-Dist: pyramid-chameleon
Requires-Dist: pyramid-jinja2
Requires-Dist: requests
Requires-Dist: shapely
Requires-Dist: sqlalchemy
Requires-Dist: zope-sqlalchemy
Project-URL: Bug Tracker, https://github.com/camptocamp/c2cgeoform/issues
Project-URL: Repository, https://github.com/camptocamp/c2cgeoform
